requirement_walker/__init__.py
requirement_walker/regex_expressions.py
requirement_walker/requirment_types.py
requirement_walker/walker.py
requirement_walker-0.0.9.dist-info/LICENSE
requirement_walker-0.0.9.dist-info/METADATA
requirement_walker-0.0.9.dist-info/WHEEL
requirement_walker-0.0.9.dist-info/top_level.txt
requirement_walker-0.0.9.dist-info/RECORD
