Metadata-Version: 2.1
Name: requirement-walker
Version: 0.0.9
Summary: Walk through requirements and comments in requirements.txt files.
Home-page: https://github.com/3mcloud/requirement-walker
Author: Alex Guckenberger
Author-email: aguckenberger@mmm.com
License: UNKNOWN
Platform: UNKNOWN
Classifier: Programming Language :: Python :: 3
Classifier: License :: OSI Approved :: BSD License
Classifier: Operating System :: OS Independent
Requires-Python: >=3.6
Provides-Extra: dev
Requires-Dist: pytest (>=5.4.1) ; extra == 'dev'
Requires-Dist: pytest-cov (>=2.8.1) ; extra == 'dev'
